wexample_wex_addon_app-0.0.55.dist-info/METADATA
wexample_wex_addon_app-0.0.55.dist-info/WHEEL
wexample_wex_addon_app-0.0.55.dist-info/entry_points.txt
wexample_wex_addon_app/__init__.py
wexample_wex_addon_app/__pycache__/__init__.py
wexample_wex_addon_app/app_addon_manager.py
wexample_wex_addon_app/commands/__init__.py
wexample_wex_addon_app/commands/__pycache__/__init__.py
wexample_wex_addon_app/commands/dependencies/__init__.py
wexample_wex_addon_app/commands/dependencies/check.py
wexample_wex_addon_app/commands/dependencies/publish.py
wexample_wex_addon_app/commands/file_state/__init__.py
wexample_wex_addon_app/commands/file_state/__pycache__/__init__.py
wexample_wex_addon_app/commands/file_state/rectify.py
wexample_wex_addon_app/commands/info/__init__.py
wexample_wex_addon_app/commands/info/__pycache__/__init__.py
wexample_wex_addon_app/commands/info/show.py
wexample_wex_addon_app/commands/libraries/__init__.py
wexample_wex_addon_app/commands/libraries/sync.py
wexample_wex_addon_app/commands/package/__init__.py
wexample_wex_addon_app/commands/package/bump.py
wexample_wex_addon_app/commands/package/commit_and_push.py
wexample_wex_addon_app/commands/package/publish.py
wexample_wex_addon_app/commands/package/publish_bumped.py
wexample_wex_addon_app/commands/registry/__init__.py
wexample_wex_addon_app/commands/registry/__pycache__/__init__.py
wexample_wex_addon_app/commands/registry/write.py
wexample_wex_addon_app/commands/setup/__init__.py
wexample_wex_addon_app/commands/setup/install.py
wexample_wex_addon_app/commands/suite/__init__.py
wexample_wex_addon_app/commands/suite/__pycache__/__init__.py
wexample_wex_addon_app/commands/suite/exec_command.py
wexample_wex_addon_app/commands/suite/exec_shell.py
wexample_wex_addon_app/commands/suite/packages.py
wexample_wex_addon_app/commands/suite/publish.py
wexample_wex_addon_app/commands/test/__init__.py
wexample_wex_addon_app/commands/test/run.py
wexample_wex_addon_app/commands/version/__init__.py
wexample_wex_addon_app/commands/version/propagate.py
wexample_wex_addon_app/common/__init__.py
wexample_wex_addon_app/config_value/__init__.py
wexample_wex_addon_app-0.0.55.dist-info/RECORD
